Metadata-Version: 2.1
Name: djcalcilib
Version: 0.0.1
Summary: A basic calculator
Author: dasham
